simplerandom/__init__.py
simplerandom/_bitcolumnmatrix/__init__.py
simplerandom/_bitcolumnmatrix/_bitcolumnmatrix_cython.cp312-win32.pyd
simplerandom/_bitcolumnmatrix/_bitcolumnmatrix_py.py
simplerandom/_version/__init__.py
simplerandom/iterators/__init__.py
simplerandom/iterators/_iterators_cython.cp312-win32.pyd
simplerandom/iterators/_iterators_py.py
simplerandom/iterators/test.py
simplerandom/random/__init__.py
simplerandom/random/_random_py.py
simplerandom-0.13.8.dist-info/licenses/LICENSE.txt
simplerandom-0.13.8.dist-info/METADATA
simplerandom-0.13.8.dist-info/WHEEL
simplerandom-0.13.8.dist-info/top_level.txt
simplerandom-0.13.8.dist-info/RECORD
