Metadata-Version: 2.4
Name: simplerandom
Version: 0.13.8
Summary: Simple random number generators
Author-email: Craig McQueen <craig@mcqueen.au>
License-Expression: MIT
Project-URL: Homepage, https://github.com/cmcqueen/simplerandom
Project-URL: Bug Tracker, https://github.com/cmcqueen/simplerandom/issues
Keywords: simple,random,pseudorandom,RNG,PRNG
Classifier: Development Status :: 5 - Production/Stable
Classifier: Intended Audience :: Developers
Classifier: Programming Language :: Python :: 3
Classifier: Programming Language :: Cython
Classifier: Topic :: Scientific/Engineering :: Mathematics
Requires-Python: >=3.6
License-File: LICENSE.txt
Dynamic: license-file
